LICENSE
README.md
livechat/__init__.py
livechat/livechat.py
livechat/livechat_window.py
livechat/popup.py
livechat/receiver.py
livechat/register.py
livechat/sender.py
livechat/assets/icons/icon.ico
livechat/assets/screenshots/screenshot_0.png
livechat/ui/livechat.ui
livechat/ui/icons/folder_open.png
livechat/ui/icons/send.png
livechat/ui/icons/sync.png
livechat-0.1.0.dist-info/METADATA
livechat-0.1.0.dist-info/WHEEL
livechat-0.1.0.dist-info/entry_points.txt
livechat-0.1.0.dist-info/licenses/LICENSE
livechat-0.1.0.dist-info/RECORD
