Metadata-Version: 2.3
Name: livechat
Version: 0.1.0
Summary: A program to display images and gif on other computers within same network.
Project-URL: Homepage, https://github.com/MaitreRenard18/Python-Live-Chat
Project-URL: Issues, https://github.com/MaitreRenard18/Python-Live-Chat/issues
Author-email: MaitreRenard18 <maitre.renardowo@gmail.com>
Classifier: Intended Audience :: End Users/Desktop
Classifier: License :: OSI Approved :: MIT License
Classifier: Natural Language :: English
Classifier: Operating System :: OS Independent
Classifier: Programming Language :: Python :: 3
Classifier: Programming Language :: Python :: 3.8
Classifier: Topic :: Communications :: Chat
Requires-Python: >=3.8
Requires-Dist: pyqt5==5.15.11
